typeform_extractor/TypeformExtractor.py
typeform_extractor/__init__.py
typeform_extractor-0.9.9.3.dist-info/LICENSE
typeform_extractor-0.9.9.3.dist-info/METADATA
typeform_extractor-0.9.9.3.dist-info/WHEEL
typeform_extractor-0.9.9.3.dist-info/top_level.txt
typeform_extractor-0.9.9.3.dist-info/RECORD
