Metadata-Version: 2.1
Name: typeform-extractor
Version: 0.9.9.3
Summary: Simple package to make data extraction from Typeform easier, analyze sentiment with AWS and calculate metrics with the data
Home-page: https://github.com/danielvivaspe/typeform-extractor
Author: Daniel Vivas
Author-email: hello@danielvivas.com
License: MIT
Keywords: typeform sentiment analysis dataframe amazon aws
Requires-Python: >=3.7
License-File: LICENSE
Requires-Dist: boto3
Requires-Dist: requests
Requires-Dist: pandas
Requires-Dist: formulas
Requires-Dist: importlib-metadata
